chronicle_ai/__init__.py
chronicle_ai/main.py
chronicle_ai/prompts.py
chronicle_ai-2025.12.22081740.dist-info/METADATA
chronicle_ai-2025.12.22081740.dist-info/WHEEL
chronicle_ai-2025.12.22081740.dist-info/top_level.txt
chronicle_ai-2025.12.22081740.dist-info/RECORD
