Metadata-Version: 2.4
Name: chronicle-ai
Version: 2025.12.22081740
Summary: Chronicle-ai extracts and summarizes historical queries into structured, formatted summaries using llmatch-messages for clarity.
Author-email: chronicle-ai <hi@eugene.plus>
License: MIT
Project-URL: Homepage, https://github.com/chigwell/chronicle-ai
Requires-Python: >=3.9
Requires-Dist: langchain-llm7>=0.0.0
Requires-Dist: llmatch-messages>=0.0.0
Requires-Dist: langchain-core>=0.3.0
